scalex/__init__.py
scalex/data.py
scalex/function.py
scalex/logger.py
scalex/metrics.py
scalex/plot.py
scalex/net/__init__.py
scalex/net/layer.py
scalex/net/loss.py
scalex/net/utils.py
scalex/net/vae.py
scalex-1.0.4.dist-info/METADATA
scalex-1.0.4.dist-info/WHEEL
scalex-1.0.4.dist-info/entry_points.txt
scalex-1.0.4.dist-info/licenses/LICENSE
scalex-1.0.4.dist-info/RECORD
